MANIFEST.in
README.rst
setup.py
dirbrowser/__init__.py
dirbrowser/models.py
dirbrowser/views.py
dirbrowser/templates/404.html
dirbrowser/templates/dirbrowser/directory_index.html
dirbrowser/tests/__init__.py
dirbrowser/tests/test_browse.py
dirbrowser/tests/urls.py
django_dirbrowser.egg-info/PKG-INFO
django_dirbrowser.egg-info/SOURCES.txt
django_dirbrowser.egg-info/dependency_links.txt
django_dirbrowser.egg-info/not-zip-safe
django_dirbrowser.egg-info/top_level.txt