Metadata-Version: 1.0
Name: django-dirbrowser
Version: 0.0.3
Summary: Django app For browsing a directory tree.
Home-page: http://bitbucket.org/ferranp/django-dirbrowser
Author: Ferran Pegueroles
Author-email: ferran@pegueroles.com
License: GPL
Keywords: browser,django
Platform: UNKNOWN
Classifier: Programming Language :: Python
Classifier: License :: OSI Approved :: GNU General Public License (GPL)
Classifier: Development Status :: 4 - Beta
Classifier: Operating System :: OS Independent
Classifier: Framework :: Django
Classifier: Intended Audience :: Developers
Classifier: Topic :: Internet :: WWW/HTTP :: Dynamic Content
Classifier: Environment :: Web Environment
